cached_interpolate/__init__.py
cached_interpolate/_version.py
cached_interpolate/build.c
cached_interpolate/build.cp312-win_amd64.pyd
cached_interpolate/build.pyx
cached_interpolate/build_jax.py
cached_interpolate/interpolate.py
cached_interpolate/matrix_forms.py
cached_interpolate/test/__init__.py
cached_interpolate/test/conftest.py
cached_interpolate/test/interpolate_test.py
cached_interpolate/test/test_jax.py
cached_interpolate-0.3.2.dist-info/LICENSE
cached_interpolate-0.3.2.dist-info/METADATA
cached_interpolate-0.3.2.dist-info/WHEEL
cached_interpolate-0.3.2.dist-info/top_level.txt
cached_interpolate-0.3.2.dist-info/RECORD
