Metadata-Version: 2.1
Name: cached_interpolate
Version: 0.3.2
Summary: Efficient repeated evaluation of splines at fixed points.
Home-page: https://github.com/ColmTalbot/cached_interpolation
Author: Colm Talbot
Author-email: colm.talbot@ligo.org
License: MIT
Classifier: Programming Language :: Python :: 3.10
Classifier: Programming Language :: Python :: 3.11
Classifier: Programming Language :: Python :: 3.12
Classifier: License :: OSI Approved :: MIT License
Classifier: Operating System :: MacOS :: MacOS X
Classifier: Operating System :: POSIX
Requires-Python: >=3.10
License-File: LICENSE
Requires-Dist: numpy
